cognite/neat/__init__.py
cognite/neat/_client/__init__.py
cognite/neat/_client/api.py
cognite/neat/_client/client.py
cognite/neat/_client/config.py
cognite/neat/_client/containers_api.py
cognite/neat/_client/data_classes.py
cognite/neat/_client/data_model_api.py
cognite/neat/_client/spaces_api.py
cognite/neat/_client/statistics_api.py
cognite/neat/_client/views_api.py
cognite/neat/_config.py
cognite/neat/_data_model/__init__.py
cognite/neat/_data_model/_analysis.py
cognite/neat/_data_model/_constants.py
cognite/neat/_data_model/_identifiers.py
cognite/neat/_data_model/_shared.py
cognite/neat/_data_model/_snapshot.py
cognite/neat/_data_model/deployer/__init__.py
cognite/neat/_data_model/deployer/_differ.py
cognite/neat/_data_model/deployer/_differ_container.py
cognite/neat/_data_model/deployer/_differ_data_model.py
cognite/neat/_data_model/deployer/_differ_space.py
cognite/neat/_data_model/deployer/_differ_view.py
cognite/neat/_data_model/deployer/data_classes.py
cognite/neat/_data_model/deployer/deployer.py
cognite/neat/_data_model/exporters/__init__.py
cognite/neat/_data_model/exporters/_api_exporter.py
cognite/neat/_data_model/exporters/_base.py
cognite/neat/_data_model/exporters/_table_exporter/__init__.py
cognite/neat/_data_model/exporters/_table_exporter/exporter.py
cognite/neat/_data_model/exporters/_table_exporter/workbook.py
cognite/neat/_data_model/exporters/_table_exporter/writer.py
cognite/neat/_data_model/importers/__init__.py
cognite/neat/_data_model/importers/_api_importer.py
cognite/neat/_data_model/importers/_base.py
cognite/neat/_data_model/importers/_table_importer/__init__.py
cognite/neat/_data_model/importers/_table_importer/data_classes.py
cognite/neat/_data_model/importers/_table_importer/importer.py
cognite/neat/_data_model/importers/_table_importer/reader.py
cognite/neat/_data_model/importers/_table_importer/source.py
cognite/neat/_data_model/models/__init__.py
cognite/neat/_data_model/models/conceptual/__init__.py
cognite_neat-1.0.20.dist-info/WHEEL
cognite_neat-1.0.20.dist-info/METADATA
cognite_neat-1.0.20.dist-info/RECORD
