Metadata-Version: 2.4
Name: cognite-neat
Version: 1.0.20
Summary: Knowledge graph transformation
Author: Nikola Vasiljevic, Anders Albert
Author-email: Nikola Vasiljevic <nikola.vasiljevic@cognite.com>, Anders Albert <anders.albert@cognite.com>
License-Expression: Apache-2.0
Classifier: Development Status :: 5 - Production/Stable
Classifier: Intended Audience :: Developers
Classifier: Intended Audience :: Information Technology
Classifier: Intended Audience :: Customer Service
Classifier: Topic :: Database
Classifier: License :: OSI Approved :: Apache Software License
Classifier: Programming Language :: Python :: 3
Classifier: Programming Language :: Python :: 3.10
Classifier: Programming Language :: Python :: 3.11
Classifier: Programming Language :: Python :: 3.12
Classifier: Programming Language :: Python :: 3.13
Classifier: Operating System :: OS Independent
Requires-Dist: pandas>=1.5.3,<3.0.0
Requires-Dist: cognite-sdk>=7.83.0,<8.0.0
Requires-Dist: rdflib>=7.0.0,<8.0.0
Requires-Dist: httpx>=0.28.1
Requires-Dist: pydantic>=2.0.0,<3.0.0
Requires-Dist: pyyaml>=6.0.1,<7.0.0
Requires-Dist: requests>=2.28.1,<3.0.0
Requires-Dist: urllib3>=1.26.15,<3.0.0
Requires-Dist: openpyxl>=3.0.10,<4.0.0
Requires-Dist: networkx>=3.4.2,<4.0.0
Requires-Dist: mixpanel>=4.10.1,<5.0.0
Requires-Dist: packaging>=22.0
Requires-Dist: jsonpath-python>=1.0.6,<2.0.0
Requires-Dist: elementpath>=4.0.0,<5.0.0
Requires-Dist: pyvis>=0.3.2,<1.0.0
Requires-Dist: rich[jupyter]>=13.7.1,<14.0.0
Requires-Dist: exceptiongroup>=1.1.3,<2.0.0 ; python_full_version < '3.11'
Requires-Dist: backports-strenum>=1.2,<2.0.0 ; python_full_version < '3.11'
Requires-Dist: typing-extensions>=4.8.0,<5.0.0 ; python_full_version < '3.11'
Requires-Dist: tomli>=2.0.1,<3.0.0 ; python_full_version < '3.11'
Requires-Dist: mkdocs>=1.4.0,<2.0.0 ; extra == 'docs'
Requires-Dist: mkdocs-jupyter>=0.25.1,<1.0.0 ; extra == 'docs'
Requires-Dist: mkdocs-material-extensions>=1.3.1,<2.0.0 ; extra == 'docs'
Requires-Dist: mkdocs-git-revision-date-localized-plugin ; extra == 'docs'
Requires-Dist: mkdocs-git-authors-plugin>=0.9.4,<1.0.0 ; extra == 'docs'
Requires-Dist: mkdocs-gitbook>=0.0.1,<1.0.0 ; extra == 'docs'
Requires-Dist: mkdocs-glightbox>=0.4.0,<1.0.0 ; extra == 'docs'
Requires-Dist: pymdown-extensions>=10.14.3,<11.0.0 ; extra == 'docs'
Requires-Dist: mkdocstrings[python]>=0.25.2,<1.0.0 ; extra == 'docs'
Requires-Dist: mistune==3.0.2 ; extra == 'docs'
Requires-Dist: mkdocs-autorefs>=0.5.0,<1.0.0 ; extra == 'docs'
Requires-Dist: gspread>=5.0.0,<6.0.0 ; extra == 'google'
Requires-Dist: google-api-python-client>=2.70.0,<3.0.0 ; extra == 'google'
Requires-Dist: google-auth-oauthlib>=1.0.0,<2.0.0 ; extra == 'google'
Requires-Dist: lxml>=5.3.0,<6.0.0 ; extra == 'lxml'
Requires-Dist: oxrdflib>=0.4.0,<0.5.0 ; extra == 'oxi'
Requires-Dist: pyoxigraph>=0.4.3,<0.5.0 ; extra == 'oxi'
Requires-Python: >=3.10
Project-URL: Changelog, https://github.com/cognitedata/neat/releases
Project-URL: Documentation, https://cognite-neat.readthedocs-hosted.com/
Project-URL: GitHub, https://github.com/cognitedata/neat
Project-URL: Homepage, https://cognite-neat.readthedocs-hosted.com/
Provides-Extra: docs
Provides-Extra: google
Provides-Extra: lxml
Provides-Extra: oxi
